{
  "source": "ozbargain_forum",
  "post_id": "964013",
  "url": "https://www.ozbargain.com.au/node/964013",
  "title": "Best ubank Alternative for Savings + BPAY?",
  "author": null,
  "body": "I’m looking to move away from ubank due to their recent changes.\nMost of my cash sits in USaver for bonus interest, but I can’t BPAY rent directly from it. I have to move money from USaver to Ultra first, then pay rent.\nThe monthly requirement to keep growing the balance also suck, can make it easy to miss bonus interest.\nAny recommendations for a bank with good everyday transactions, savings interest, simple BPAY/rent payments, fewer hoops, good interest and no monthly balance growth requirement?",
  "board": "Financial",
  "created_at": null,
  "fetched_at": "2026-06-26T20:43:28.133748Z",
  "score": null,
  "num_comments": null,
  "tags": [],
  "relevance": 1,
  "content_hash": "56160eff646fc9b2",
  "key": "ozbargain_forum:964013"
}