{
  "source": "ozbargain_comments",
  "post_id": "965473",
  "url": "https://www.ozbargain.com.au/node/965473",
  "title": "Samsung Odyssey OLED G5 27\" QHD 180Hz OLED Gaming Monitor $397 Delivered @ Amazon AU / Bing Lee",
  "author": null,
  "body": "Deal: Samsung Odyssey OLED G5 27\" QHD 180Hz OLED Gaming Monitor $397 Delivered @ Amazon AU / Bing Lee\n\n[The Value] Another option.\nAlienware AW2726DM 27\" 1440p 240Hz QD-OLED Gaming Monitor $390.41 Delivered @ Dell\nhttps://www.ozbargain.com.au/node/964238\nNo opinion.\n[JacobAU] $377 for an OLED is pretty good. Good to see OLEDs coming down in price unlike everything else. If I could put up with 27” I’d pick this up in a heartbeat\n[ValenHuang] Did some research on this panel: all-panel brightness 226 nit, with peak 357 nit. So technically it is very close to a HDR400 OLED.\nHowever you have to choose from running 2k 120hz with 10-bit or 2k 180hz with 8-bit.\n[Yer] Wow they cheeped out. Running DP 1.2 and HDMI 2.0. What year we in…\n[Ranike] Latest firmware actually unlocks the dp to 1.4 so you can get 2k 180hz 10-bit\n[djuice] Typical max brightness of around 200 nits~ in SDR mode, is way below most modern VA/IPS LED monitors which have around 350-400 nits. It's not going to be very bright, and might have issues using it during daytime in a semi-lit room.\n[tp0] 200 nits is more than enough for a PC monitor in any indoor environment.\n[Yer] I suggest getting the AW2726DM mentioned above . The G5 has a matte coating that multiplies the raised blacks in these generations of QD OLED.\n[RachC] Is this one recommend for good budget 5070 Iracing player?\n[Wonderfool] I was waiting for the mini led monitors, but with OLED prices this low, might not need it.\n[FlipperMeTimbers] i got this for ~$350 after an amex samsung deal, i like the matte anti reflection coating as my desk is near a window and it makes the low brightness really negligible. often times i dont even run it at full brightness. wish it had usbc hub\n[motion2082] I feel like OLED is one of those technologies where margins are huge for companies like MSI and Asus selling the premium OLEDs. Especially when you see a lot more brands selling OLED for under $1000K\n[TechNo1geek] $2 cheaper than Kogan Omega OLED (with kogan First), which one should i get?\n[jordnz] good question. Kogan looks like it's using a Samsung panel but has 280Hz and 250 nits brightness so.. looks better on paper than this?\n[pinkybrain] looks better on paper than this?\nit's a Kogan !!",
  "board": "OzBargain Deals (comments)",
  "created_at": null,
  "fetched_at": "2026-06-28T16:46:15.142806Z",
  "score": null,
  "num_comments": 16,
  "tags": [],
  "relevance": 2,
  "content_hash": "14fa43a53a94e848",
  "key": "ozbargain_comments:965473"
}